nature/404.html
nature/__init__.py
nature/base.html
nature/main.html
nature/mkdocs_theme.yml
nature/search.html
nature/sitemap.html
nature/static/basic.css
nature/static/doctools.js
nature/static/file.png
nature/static/github.png
nature/static/jquery.js
nature/static/nature.css
nature/static/pygments.css
nature/static/underscore.js
mkdocs_nature-0.6.dist-info/LICENSE
mkdocs_nature-0.6.dist-info/METADATA
mkdocs_nature-0.6.dist-info/WHEEL
mkdocs_nature-0.6.dist-info/entry_points.txt
mkdocs_nature-0.6.dist-info/top_level.txt
mkdocs_nature-0.6.dist-info/RECORD
