Metadata-Version: 2.1
Name: mkdocs-nature
Version: 0.6
Summary: A MkDocs theme. A clone of the "greenish" Sphinx theme of the same name.
Home-page: https://waylan.github.io/mkdocs-nature/
Author: Waylan Limberg
Author-email: waylan.limberg@icloud.com
License: BSD
License-File: LICENSE
Requires-Dist: mkdocs >=1.0
